[
  {
    "name": "용두암하이킹",
    "rentalType": "유료대여소",
    "address": "제주특별자치도 제주시 삼도2동 1115",
    "latitude": "33.5156722",
    "longitude": "126.5215176",
    "startTime": "9:00",
    "endTime": "18:00",
    "closedDays": "없음",
    "payType": "유료",
    "charge": "2000원",
    "numberOfBicycle": 8,
    "airInjection": false,
    "airInjectionType": "",
    "repairstand": false,
    "managerNumber": "064-757-7777",
    "manager": "",
    "thumbUrl": "http://ldb.phinf.naver.net/20150901_253/1441035132808jmo8r_JPEG/12892839_0.jpg"
  },
  {
    "name": "수월봉전기자전거",
    "rentalType": "유료대여소",
    "address": "제주특별자치도 제주시 한경면 고산리 3674-9",
    "latitude": "33.2988265",
    "longitude": "126.1680307",
    "startTime": "9:00",
    "endTime": "18:00",
    "closedDays": "없음",
    "payType": "유료",
    "charge": "3000원",
    "numberOfBicycle": 19,
    "airInjection": false,
    "airInjectionType": "",
    "repairstand": false,
    "managerNumber": "010-7591-7388",
    "manager": "",
    "thumbUrl": "http://ldb.phinf.naver.net/20170824_253/1503550440247hR96K_JPEG/q1ZyVQAiNbyuclp5vTHOaSdc.JPG.jpg"
  },
  {
    "name": "제주도자전거대여보물섬하이킹",
    "rentalType": "유료대여소",
    "address": "제주특별자치도 제주시 용담2동 2706-1",
    "latitude": "33.5059902",
    "longitude": "126.5100313",
    "startTime": "9:00",
    "endTime": "18:00",
    "closedDays": "없음",
    "payType": "유료",
    "charge": "2000원",
    "numberOfBicycle": 9,
    "airInjection": false,
    "airInjectionType": "",
    "repairstand": false,
    "managerNumber": "010-4582-8240",
    "manager": "",
    "thumbUrl": "http://ldb.phinf.naver.net/20160406_77/14599239321764RvSj_PNG/176353566569296_0.png"
  },
  {
    "name": "타발로하이킹",
    "rentalType": "유료대여소",
    "address": "제주특별자치도 제주시 이도2동 387-5",
    "latitude": "33.4982629",
    "longitude": "126.5387661",
    "startTime": "9:00",
    "endTime": "18:00",
    "closedDays": "없음",
    "payType": "유료",
    "charge": "4000원",
    "numberOfBicycle": 18,
    "airInjection": false,
    "airInjectionType": "",
    "repairstand": false,
    "managerNumber": "010-7304-4996",
    "manager": "",
    "thumbUrl": "http://ldb.phinf.naver.net/20151113_160/1447396794530zmVpG_JPEG/167154463577713_6.jpg"
  },
  {
    "name": "바이크트립",
    "rentalType": "유료대여소",
    "address": "제주특별자치도 제주시 용담2동 1543-3",
    "latitude": "33.5046308",
    "longitude": "126.4987662",
    "startTime": "9:00",
    "endTime": "18:00",
    "closedDays": "없음",
    "payType": "유료",
    "charge": "7000원",
    "numberOfBicycle": 11,
    "airInjection": false,
    "airInjectionType": "",
    "repairstand": false,
    "managerNumber": "064-744-5990",
    "manager": "",
    "thumbUrl": "http://ldb.phinf.naver.net/20160112_45/1452555032442kWbsS_JPEG/176062486050878_0.jpeg"
  },
  {
    "name": "제주하이킹",
    "rentalType": "유료대여소",
    "address": "제주특별자치도 제주시 용담3동 1029-3",
    "latitude": "33.5168360",
    "longitude": "126.5023520",
    "startTime": "9:00",
    "endTime": "18:00",
    "closedDays": "없음",
    "payType": "유료",
    "charge": "3000원",
    "numberOfBicycle": 6,
    "airInjection": false,
    "airInjectionType": "",
    "repairstand": false,
    "managerNumber": "064-711-2200",
    "manager": "",
    "thumbUrl": "http://ldb.phinf.naver.net/20150831_286/1440994256762GxWxF_JPEG/126680414849369_0.jpg"
  },
  {
    "name": "우도하이킹레저",
    "rentalType": "유료대여소",
    "address": "제주특별자치도 제주시 우도면 연평리 2395-3",
    "latitude": "33.5092667",
    "longitude": "126.9433500",
    "startTime": "9:00",
    "endTime": "18:00",
    "closedDays": "없음",
    "payType": "유료",
    "charge": "3000원",
    "numberOfBicycle": 18,
    "airInjection": false,
    "airInjectionType": "",
    "repairstand": false,
    "managerNumber": "064-782-5931",
    "manager": "",
    "thumbUrl": null
  },
  {
    "name": "자전거빌리지",
    "rentalType": "유료대여소",
    "address": "제주특별자치도 제주시 일도2동 141",
    "latitude": "33.5131885",
    "longitude": "126.5421219",
    "startTime": "9:00",
    "endTime": "18:00",
    "closedDays": "없음",
    "payType": "유료",
    "charge": "6000원",
    "numberOfBicycle": 10,
    "airInjection": false,
    "airInjectionType": "",
    "repairstand": false,
    "managerNumber": "010-3100-1414",
    "manager": "",
    "thumbUrl": null
  },
  {
    "name": "제주자전거대여점",
    "rentalType": "유료대여소",
    "address": "제주특별자치도 제주시 건입동 1043-2 1층",
    "latitude": "33.5157137",
    "longitude": "126.5368666",
    "startTime": "9:00",
    "endTime": "18:00",
    "closedDays": "없음",
    "payType": "유료",
    "charge": "7000원",
    "numberOfBicycle": 14,
    "airInjection": false,
    "airInjectionType": "",
    "repairstand": false,
    "managerNumber": "010-4932-5949",
    "manager": "",
    "thumbUrl": null
  },
  {
    "name": "환타지제주",
    "rentalType": "유료대여소",
    "address": "제주특별자치도 서귀포시 색달동 2864-36",
    "latitude": "33.2501938",
    "longitude": "126.4128508",
    "startTime": "9:00",
    "endTime": "18:00",
    "closedDays": "없음",
    "payType": "유료",
    "charge": "5000원",
    "numberOfBicycle": 16,
    "airInjection": false,
    "airInjectionType": "",
    "repairstand": false,
    "managerNumber": "010-6693-7189",
    "manager": "",
    "thumbUrl": "http://ldb.phinf.naver.net/20150901_96/14410597489094uLMz_GIF/SUBMIT_1382491275326_33461072.gif"
  },
  {
    "name": "로얄쇼핑자전거대여소",
    "rentalType": "유료대여소",
    "address": "제주특별자치도 제주시 연동",
    "latitude": "33.4891944",
    "longitude": "126.4909367",
    "startTime": "9:00",
    "endTime": "18:00",
    "closedDays": "없음",
    "payType": "유료",
    "charge": "4000원",
    "numberOfBicycle": 11,
    "airInjection": false,
    "airInjectionType": "",
    "repairstand": false,
    "managerNumber": "",
    "manager": "",
    "thumbUrl": null
  },
  {
    "name": "아이러브바이크",
    "rentalType": "유료대여소",
    "address": "제주특별자치도 제주시 삼도2동 14-4",
    "latitude": "33.5158840",
    "longitude": "126.5226770",
    "startTime": "9:00",
    "endTime": "18:00",
    "closedDays": "없음",
    "payType": "유료",
    "charge": "6000원",
    "numberOfBicycle": 13,
    "airInjection": false,
    "airInjectionType": "",
    "repairstand": false,
    "managerNumber": "064-723-7775",
    "manager": "",
    "thumbUrl": "http://ldb.phinf.naver.net/20150901_217/1441041448164Db3Gm_JPEG/126662557272657_0.jpg"
  },
  {
    "name": "아트센터(한라도서관)자전거대여소",
    "rentalType": "유료대여소",
    "address": "제주특별자치도 제주시 오라2동",
    "latitude": "33.4756553",
    "longitude": "126.5145154",
    "startTime": "9:00",
    "endTime": "18:00",
    "closedDays": "없음",
    "payType": "유료",
    "charge": "6000원",
    "numberOfBicycle": 16,
    "airInjection": false,
    "airInjectionType": "",
    "repairstand": false,
    "managerNumber": "",
    "manager": "",
    "thumbUrl": null
  },
  {
    "name": "탐라도서관자전거대여소",
    "rentalType": "유료대여소",
    "address": "제주특별자치도 제주시 노형동",
    "latitude": "33.4778949",
    "longitude": "126.4775358",
    "startTime": "9:00",
    "endTime": "18:00",
    "closedDays": "없음",
    "payType": "유료",
    "charge": "5000원",
    "numberOfBicycle": 12,
    "airInjection": false,
    "airInjectionType": "",
    "repairstand": false,
    "managerNumber": "",
    "manager": "",
    "thumbUrl": null
  },
  {
    "name": "(구)제주일보사자전거대여소",
    "rentalType": "유료대여소",
    "address": "제주특별자치도 제주시 연동",
    "latitude": "33.4908578",
    "longitude": "126.4859025",
    "startTime": "9:00",
    "endTime": "18:00",
    "closedDays": "없음",
    "payType": "유료",
    "charge": "4000원",
    "numberOfBicycle": 19,
    "airInjection": false,
    "airInjectionType": "",
    "repairstand": false,
    "managerNumber": "",
    "manager": "",
    "thumbUrl": null
  },
  {
    "name": "제이바이시클",
    "rentalType": "유료대여소",
    "address": "제주특별자치도 제주시 용담1동 220-14 1층",
    "latitude": "33.5092130",
    "longitude": "126.5160238",
    "startTime": "9:00",
    "endTime": "18:00",
    "closedDays": "없음",
    "payType": "유료",
    "charge": "6000원",
    "numberOfBicycle": 14,
    "airInjection": false,
    "airInjectionType": "",
    "repairstand": false,
    "managerNumber": "010-4626-5815",
    "manager": "",
    "thumbUrl": "http://ldb.phinf.naver.net/20170110_198/1484035134609abIro_PNG/186055578533709_0.png"
  },
  {
    "name": "중문하이킹",
    "rentalType": "유료대여소",
    "address": "제주특별자치도 서귀포시 색달동 2502-1",
    "latitude": "33.2552878",
    "longitude": "126.4146759",
    "startTime": "9:00",
    "endTime": "18:00",
    "closedDays": "없음",
    "payType": "유료",
    "charge": "2000원",
    "numberOfBicycle": 7,
    "airInjection": false,
    "airInjectionType": "",
    "repairstand": false,
    "managerNumber": "064-739-3500",
    "manager": "",
    "thumbUrl": null
  },
  {
    "name": "국기로(대림A)자전거대여소",
    "rentalType": "유료대여소",
    "address": "제주특별자치도 제주시 연동",
    "latitude": "33.4785140",
    "longitude": "126.4906762",
    "startTime": "9:00",
    "endTime": "18:00",
    "closedDays": "없음",
    "payType": "유료",
    "charge": "2000원",
    "numberOfBicycle": 7,
    "airInjection": false,
    "airInjectionType": "",
    "repairstand": false,
    "managerNumber": "",
    "manager": "",
    "thumbUrl": null
  },
  {
    "name": "설문대여성문화센터자전거대여소",
    "rentalType": "유료대여소",
    "address": "제주특별자치도 제주시 연동",
    "latitude": "33.4840719",
    "longitude": "126.5000440",
    "startTime": "9:00",
    "endTime": "18:00",
    "closedDays": "없음",
    "payType": "유료",
    "charge": "7000원",
    "numberOfBicycle": 10,
    "airInjection": false,
    "airInjectionType": "",
    "repairstand": false,
    "managerNumber": "",
    "manager": "",
    "thumbUrl": null
  },
  {
    "name": "성산라이딩",
    "rentalType": "유료대여소",
    "address": "제주특별자치도 서귀포시 성산읍 성산리 230-4",
    "latitude": "33.4646036",
    "longitude": "126.9333719",
    "startTime": "9:00",
    "endTime": "18:00",
    "closedDays": "없음",
    "payType": "유료",
    "charge": "5000원",
    "numberOfBicycle": 6,
    "airInjection": false,
    "airInjectionType": "",
    "repairstand": false,
    "managerNumber": "010-5236-9000",
    "manager": "",
    "thumbUrl": "http://ldb.phinf.naver.net//20170704_127/1499132933756dQ7T2_JPEG/%BC%BA%BB%EA_%B6%F3%C0%CC%B5%F9.jpg"
  },
  {
    "name": "푸른바이크쉐어링",
    "rentalType": "유료대여소",
    "address": "제주특별자치도 제주시 삼도2동 967",
    "latitude": "33.5123941",
    "longitude": "126.5213416",
    "startTime": "9:00",
    "endTime": "18:00",
    "closedDays": "없음",
    "payType": "유료",
    "charge": "5000원",
    "numberOfBicycle": 17,
    "airInjection": false,
    "airInjectionType": "",
    "repairstand": false,
    "managerNumber": "064-721-0333",
    "manager": "",
    "thumbUrl": null
  },
  {
    "name": "에코트립",
    "rentalType": "유료대여소",
    "address": "제주특별자치도 제주시 삼도2동 1158-44",
    "latitude": "33.5148228",
    "longitude": "126.5178852",
    "startTime": "9:00",
    "endTime": "18:00",
    "closedDays": "없음",
    "payType": "유료",
    "charge": "5000원",
    "numberOfBicycle": 12,
    "airInjection": false,
    "airInjectionType": "",
    "repairstand": false,
    "managerNumber": "1800-5816",
    "manager": "",
    "thumbUrl": null
  },
  {
    "name": "에코트립",
    "rentalType": "유료대여소",
    "address": "제주특별자치도 서귀포시 강정동 2637-1",
    "latitude": "33.2344160",
    "longitude": "126.4882685",
    "startTime": "9:00",
    "endTime": "18:00",
    "closedDays": "없음",
    "payType": "유료",
    "charge": "3000원",
    "numberOfBicycle": 7,
    "airInjection": false,
    "airInjectionType": "",
    "repairstand": false,
    "managerNumber": "070-7124-0938",
    "manager": "",
    "thumbUrl": "http://ldb.phinf.naver.net/20170216_12/1487235233664IWKed_JPEG/186164547334306_0.jpeg"
  },
  {
    "name": "아일랜드하이킹",
    "rentalType": "유료대여소",
    "address": "제주특별자치도 제주시 용담1동 308-4",
    "latitude": "33.5108896",
    "longitude": "126.5129566",
    "startTime": "9:00",
    "endTime": "18:00",
    "closedDays": "없음",
    "payType": "유료",
    "charge": "7000원",
    "numberOfBicycle": 12,
    "airInjection": false,
    "airInjectionType": "",
    "repairstand": false,
    "managerNumber": "064-900-6111",
    "manager": "",
    "thumbUrl": null
  },
  {
    "name": "헬로우제주 전동킥보드",
    "rentalType": "유료대여소",
    "address": "제주특별자치도 서귀포시 안덕면 덕수리 2772-1",
    "latitude": "33.2662181",
    "longitude": "126.3006345",
    "startTime": "9:00",
    "endTime": "18:00",
    "closedDays": "없음",
    "payType": "유료",
    "charge": "2000원",
    "numberOfBicycle": 8,
    "airInjection": false,
    "airInjectionType": "",
    "repairstand": false,
    "managerNumber": "010-7329-9069",
    "manager": "",
    "thumbUrl": "http://ldb.phinf.naver.net/20170714_192/1499999670053GErkq_JPEG/186662547454458_0.jpeg"
  },
  {
    "name": "하우마을레저",
    "rentalType": "유료대여소",
    "address": "제주특별자치도 제주시 우도면 연평리 2384-5",
    "latitude": "33.5097363",
    "longitude": "126.9434747",
    "startTime": "9:00",
    "endTime": "18:00",
    "closedDays": "없음",
    "payType": "유료",
    "charge": "6000원",
    "numberOfBicycle": 9,
    "airInjection": false,
    "airInjectionType": "",
    "repairstand": false,
    "managerNumber": "064-783-0354",
    "manager": "",
    "thumbUrl": null
  },
  {
    "name": "자전거빌리지",
    "rentalType": "유료대여소",
    "address": "제주특별자치도 제주시 일도2동 141",
    "latitude": "33.5131970",
    "longitude": "126.5420954",
    "startTime": "9:00",
    "endTime": "18:00",
    "closedDays": "없음",
    "payType": "유료",
    "charge": "7000원",
    "numberOfBicycle": 18,
    "airInjection": false,
    "airInjectionType": "",
    "repairstand": false,
    "managerNumber": "070-8790-7100",
    "manager": "",
    "thumbUrl": null
  },
  {
    "name": "제주라이더",
    "rentalType": "유료대여소",
    "address": "제주특별자치도 제주시 일도1동 1100-10",
    "latitude": "33.5127614",
    "longitude": "126.5282562",
    "startTime": "9:00",
    "endTime": "18:00",
    "closedDays": "없음",
    "payType": "유료",
    "charge": "6000원",
    "numberOfBicycle": 13,
    "airInjection": false,
    "airInjectionType": "",
    "repairstand": false,
    "managerNumber": "010-8459-2848",
    "manager": "",
    "thumbUrl": "http://ldb.phinf.naver.net/20150901_199/1441101112111mfcCh_JPEG/156265605969357_0.jpeg"
  },
  {
    "name": "우도팔경레져",
    "rentalType": "유료대여소",
    "address": "제주특별자치도 제주시 우도면 연평리 1737-3",
    "latitude": "33.4926222",
    "longitude": "126.9519664",
    "startTime": "9:00",
    "endTime": "18:00",
    "closedDays": "없음",
    "payType": "유료",
    "charge": "4000원",
    "numberOfBicycle": 15,
    "airInjection": false,
    "airInjectionType": "",
    "repairstand": false,
    "managerNumber": "010-2604-3096",
    "manager": "",
    "thumbUrl": "http://ldb.phinf.naver.net/20160517_35/1463458899379uXdc2_JPEG/176457536265051_2.jpeg"
  },
  {
    "name": "한라싸이클",
    "rentalType": "유료대여소",
    "address": "제주특별자치도 제주시 오라2동 3160",
    "latitude": "33.4814673",
    "longitude": "126.5012949",
    "startTime": "9:00",
    "endTime": "18:00",
    "closedDays": "없음",
    "payType": "유료",
    "charge": "2000원",
    "numberOfBicycle": 19,
    "airInjection": false,
    "airInjectionType": "",
    "repairstand": false,
    "managerNumber": "064-749-8510",
    "manager": "",
    "thumbUrl": "http://ldb.phinf.naver.net/20150831_43/1441018036161M8WPf_JPEG/166579548678955_0.jpeg"
  },
  {
    "name": "바이크스토리",
    "rentalType": "유료대여소",
    "address": "제주특별자치도 제주시 삼양2동 2129-7",
    "latitude": "33.5213974",
    "longitude": "126.5818624",
    "startTime": "9:00",
    "endTime": "18:00",
    "closedDays": "없음",
    "payType": "유료",
    "charge": "5000원",
    "numberOfBicycle": 20,
    "airInjection": false,
    "airInjectionType": "",
    "repairstand": false,
    "managerNumber": "064-723-7757",
    "manager": "",
    "thumbUrl": "http://ldb.phinf.naver.net/20150901_15/1441060951460h0v20_JPEG/166656588345924_0.jpeg"
  },
  {
    "name": "그린스퀘어",
    "rentalType": "유료대여소",
    "address": "제주특별자치도 제주시 건입동 1451-5",
    "latitude": "33.5275000",
    "longitude": "126.5450000",
    "startTime": "9:00",
    "endTime": "18:00",
    "closedDays": "없음",
    "payType": "유료",
    "charge": "5000원",
    "numberOfBicycle": 15,
    "airInjection": false,
    "airInjectionType": "",
    "repairstand": false,
    "managerNumber": "064-757-5679",
    "manager": "",
    "thumbUrl": "http://ldb.phinf.naver.net/20170306_108/1488764451166dA2Ve_JPEG/186175584851040_0.jpeg"
  }
]